{
    "backend": "api-server-flask",
    "db_name": "",
    "db_pass": "",
    "db_type": "sqlite",
    "db_user": "",
    "dbms": "1",
    "description": "generated product",
    "design": "berry-dashboard",
    "docker": "1",
    "err_code": 0,
    "frontend": "react",
    "heroku": "0",
    "pattern": "fullstack",
    "pro": "0",
    "task_id": "0618bdea-4986-4671-ace8-0d259522f651",
    "task_info": "Upload Sources [0%] - 136 files",
    "task_output": "0618bdea-4986-4671-ace8-0d259522f651.zip",
    "task_result": "SUCCESS",
    "task_state": "RUNNING",
    "task_ts_end": "2023-08-22-16-03-26",
    "task_ts_start": "2023-08-22-16-03-25"
}